yta_audio_base/__init__.py
yta_audio_base/audio.py
yta_audio_base/channels/__init__.py
yta_audio_base/channels/utils.py
yta_audio_base/converter.py
yta_audio_base/dataclasses.py
yta_audio_base/duration.py
yta_audio_base/noise.py
yta_audio_base/numpy.py
yta_audio_base/parser/__init__.py
yta_audio_base/parser/utils.py
yta_audio_base/saver.py
yta_audio_base/separator.py
yta_audio_base/volume/__init__.py
yta_audio_base/volume/utils.py
yta_audio_base-0.1.6.dist-info/licenses/LICENSE
yta_audio_base-0.1.6.dist-info/METADATA
yta_audio_base-0.1.6.dist-info/WHEEL
yta_audio_base-0.1.6.dist-info/RECORD
