Metadata-Version: 2.4
Name: yta-audio-base
Version: 0.1.6
Summary: Youtube Autonomous Basic Audio Module.
License-File: LICENSE
Author: danialcala94
Author-email: danielalcalavalera@gmail.com
Requires-Python: ==3.9
Classifier: Programming Language :: Python :: 3
Classifier: Programming Language :: Python :: 3.9
Requires-Dist: deepfilternet (>=0.5.6,<9.0.0)
Requires-Dist: librosa (>=0.0.1,<9.0.0)
Requires-Dist: numpy (>=0.0.1,<9.0.0)
Requires-Dist: pydub (>=0.25.1,<1.0.0)
Requires-Dist: yta_constants (>=0.0.1,<1.0.0)
Requires-Dist: yta_file (>=0.0.1,<1.0.0)
Requires-Dist: yta_general (>=0.0.1,<1.0.0)
Requires-Dist: yta_numpy (>=0.0.1,<1.0.0)
Requires-Dist: yta_programming (>=0.0.1,<1.0.0)
Requires-Dist: yta_programming_path (>=0.0.1,<1.0.0)
Requires-Dist: yta_validation (>=0.0.1,<1.0.0)
